LICENSE
MANIFEST.in
README.md
README.rst
setup.py
augtxt/__init__.py
augtxt/augmenters.py
augtxt/keyboard_layouts.py
augtxt/order.py
augtxt/punct.py
augtxt/typo.py
augtxt/wordsubs.py
augtxt.egg-info/PKG-INFO
augtxt.egg-info/SOURCES.txt
augtxt.egg-info/dependency_links.txt
augtxt.egg-info/requires.txt
augtxt.egg-info/top_level.txt
augtxt.egg-info/zip-safe
test/__init__.py
test/test_order.py
test/test_punct_merge_words.py
test/test_punct_syntaxinfo.py
test/test_senttypo.py
test/test_typo_drop_char.py
test/test_typo_drop_n_next_twice.py
test/test_typo_pressed_shiftalt.py
test/test_typo_pressed_twice.py
test/test_typo_swap_consecutive.py
test/test_wordtypo.py