Metadata-Version: 2.1
Name: augtxt
Version: 0.5.1
Summary: Text augmentation.
Home-page: http://github.com/ulf1/augtxt
Author: Ulf Hamster
Author-email: 554c46@gmail.com
License: Apache License 2.0
Platform: UNKNOWN
Requires-Python: >=3.6
License-File: LICENSE
